{
    "id": "slack",
    "name": "Slack",
    "description": {
        "fr_FR": "Plugin pour lier Jeedom à Slack",
        "en_US": "Plugin to link Jeedom to Slack",
        "es_ES": "Complemento para vincular Jeedom a Slack",
        "de_DE": "Plugin, um Jeedom mit Slack zu verbinden",
        "pt_PT": "Plugin para vincular o Jeedom ao Slack"
    },
    "licence": "AGPL",
    "author": "Loïc",
    "require": "3.0",
    "category": "communication",
    "changelog": "https:\/\/doc.jeedom.com\/#language#\/plugins\/communication\/slack\/changelog",
    "documentation": "https:\/\/doc.jeedom.com\/#language#\/plugins\/communication\/slack\/",
    "language": [
        "fr_FR",
        "en_US",
        "es_ES",
        "de_DE",
        "pt_PT"
    ],
    "compatibility": [
        "miniplus",
        "smart",
        "rpi",
        "docker",
        "diy",
        "mobile",
        "v4"
    ]
}